{"meta":{"span":{"rangeFrom":16970000,"rangeTo":16983768},"structure":{"convictionVoting":["delegate","undelegate","vote","removeVote","removeOtherVote"],"referenda":["submit"]}},"data":{"16970575":{"convictionVoting":{"vote":{"index":0,"signer":"HvumdQbk47PXTz57UDrZP5n8rmgf27upC1ooPjtZf9XA2Wk","args":["122","{\"standard\":{\"vote\":\"0x81\",\"balance\":50000000000000}}"],"events":[{"section":"system","method":"ExtrinsicSuccess","data":[{"weight":{"refTime":"255,250,000","proofSize":"0"},"class":"Mandatory","paysFee":"Yes"}]}]}}},"16970577":{"convictionVoting":{"vote":{"index":0,"signer":"JHwBvr7JeNXW8S8JL7wumsvqYZ8Kf2W1xrYn5nS1Z8p81VL","args":["122","{\"standard\":{\"vote\":\"0x81\",\"balance\":50000000000000}}"],"events":[{"section":"system","method":"ExtrinsicSuccess","data":[{"weight":{"refTime":"255,250,000","proofSize":"0"},"class":"Mandatory","paysFee":"Yes"}]}]}}},"16971361":{"convictionVoting":{"vote":{"index":0,"signer":"FfbGaF1B6hNMPNKcjgyciU2RqbAgF8UmW1dAxTi667odgR5","args":["121","{\"standard\":{\"vote\":\"0x81\",\"balance\":10000000000000}}"],"events":[{"section":"system","method":"ExtrinsicSuccess","data":[{"weight":{"refTime":"255,250,000","proofSize":"0"},"class":"Mandatory","paysFee":"Yes"}]}]}}},"16971369":{"convictionVoting":{"vote":{"index":0,"signer":"FfbGaF1B6hNMPNKcjgyciU2RqbAgF8UmW1dAxTi667odgR5","args":["122","{\"standard\":{\"vote\":\"0x81\",\"balance\":10000000000000}}"],"events":[{"section":"system","method":"ExtrinsicSuccess","data":[{"weight":{"refTime":"255,250,000","proofSize":"0"},"class":"Mandatory","paysFee":"Yes"}]}]}}},"16971374":{"convictionVoting":{"vote":{"index":0,"signer":"FkPMVMcppToPSdMEohDxhhZYWpYY2ZwfgEaBNog9Vj2f61o","args":["121","{\"standard\":{\"vote\":\"0x81\",\"balance\":30000000000000}}"],"events":[{"section":"system","method":"ExtrinsicSuccess","data":[{"weight":{"refTime":"255,250,000","proofSize":"0"},"class":"Mandatory","paysFee":"Yes"}]}]}}},"16971376":{"convictionVoting":{"vote":{"index":0,"signer":"FkPMVMcppToPSdMEohDxhhZYWpYY2ZwfgEaBNog9Vj2f61o","args":["122","{\"standard\":{\"vote\":\"0x81\",\"balance\":30000000000000}}"],"events":[{"section":"system","method":"ExtrinsicSuccess","data":[{"weight":{"refTime":"255,250,000","proofSize":"0"},"class":"Mandatory","paysFee":"Yes"}]}]}}},"16971405":{"convictionVoting":{"vote":{"index":0,"signer":"HnqvLipy4zndzJcJWAVJDpDWNMR6ygTVDRym5BeapXHLS2K","args":["122","{\"standard\":{\"vote\":\"0x81\",\"balance\":45000000000000}}"],"events":[{"section":"system","method":"ExtrinsicSuccess","data":[{"weight":{"refTime":"255,250,000","proofSize":"0"},"class":"Mandatory","paysFee":"Yes"}]}]}}},"16971949":{"convictionVoting":{"vote":{"index":0,"signer":"H52wVBJVjfRvqfq1wimsYNLFPqpiBDXLBy4i9ozCFzj7YMx","args":["109","{\"standard\":{\"vote\":\"0x00\",\"balance\":0}}"],"events":[{"section":"system","method":"ExtrinsicSuccess","data":[{"weight":{"refTime":"255,250,000","proofSize":"0"},"class":"Mandatory","paysFee":"Yes"}]}]}}},"16971951":{"convictionVoting":{"vote":{"index":0,"signer":"H52wVBJVjfRvqfq1wimsYNLFPqpiBDXLBy4i9ozCFzj7YMx","args":["111","{\"standard\":{\"vote\":\"0x00\",\"balance\":0}}"],"events":[{"section":"system","method":"ExtrinsicSuccess","data":[{"weight":{"refTime":"255,250,000","proofSize":"0"},"class":"Mandatory","paysFee":"Yes"}]}]}}},"16971958":{"convictionVoting":{"vote":{"index":0,"signer":"H52wVBJVjfRvqfq1wimsYNLFPqpiBDXLBy4i9ozCFzj7YMx","args":["112","{\"standard\":{\"vote\":\"0x00\",\"balance\":0}}"],"events":[{"section":"system","method":"ExtrinsicSuccess","data":[{"weight":{"refTime":"255,250,000","proofSize":"0"},"class":"Mandatory","paysFee":"Yes"}]}]}}},"16971961":{"convictionVoting":{"vote":{"index":0,"signer":"H52wVBJVjfRvqfq1wimsYNLFPqpiBDXLBy4i9ozCFzj7YMx","args":["114","{\"standard\":{\"vote\":\"0x00\",\"balance\":0}}"],"events":[{"section":"system","method":"ExtrinsicSuccess","data":[{"weight":{"refTime":"255,250,000","proofSize":"0"},"class":"Mandatory","paysFee":"Yes"}]}]}}},"16971965":{"convictionVoting":{"vote":{"index":0,"signer":"H52wVBJVjfRvqfq1wimsYNLFPqpiBDXLBy4i9ozCFzj7YMx","args":["115","{\"standard\":{\"vote\":\"0x00\",\"balance\":0}}"],"events":[{"section":"system","method":"ExtrinsicSuccess","data":[{"weight":{"refTime":"255,250,000","proofSize":"0"},"class":"Mandatory","paysFee":"Yes"}]}]}}},"16971968":{"convictionVoting":{"vote":{"index":0,"signer":"H52wVBJVjfRvqfq1wimsYNLFPqpiBDXLBy4i9ozCFzj7YMx","args":["117","{\"standard\":{\"vote\":\"0x00\",\"balance\":0}}"],"events":[{"section":"system","method":"ExtrinsicSuccess","data":[{"weight":{"refTime":"255,250,000","proofSize":"0"},"class":"Mandatory","paysFee":"Yes"}]}]}}},"16971973":{"convictionVoting":{"vote":{"index":0,"signer":"H52wVBJVjfRvqfq1wimsYNLFPqpiBDXLBy4i9ozCFzj7YMx","args":["121","{\"standard\":{\"vote\":\"0x00\",\"balance\":0}}"],"events":[{"section":"system","method":"ExtrinsicSuccess","data":[{"weight":{"refTime":"255,250,000","proofSize":"0"},"class":"Mandatory","paysFee":"Yes"}]}]}}},"16971977":{"convictionVoting":{"vote":{"index":0,"signer":"H52wVBJVjfRvqfq1wimsYNLFPqpiBDXLBy4i9ozCFzj7YMx","args":["119","{\"standard\":{\"vote\":\"0x00\",\"balance\":0}}"],"events":[{"section":"system","method":"ExtrinsicSuccess","data":[{"weight":{"refTime":"255,250,000","proofSize":"0"},"class":"Mandatory","paysFee":"Yes"}]}]}}},"16971980":{"convictionVoting":{"vote":{"index":0,"signer":"H52wVBJVjfRvqfq1wimsYNLFPqpiBDXLBy4i9ozCFzj7YMx","args":["118","{\"standard\":{\"vote\":\"0x00\",\"balance\":0}}"],"events":[{"section":"system","method":"ExtrinsicSuccess","data":[{"weight":{"refTime":"255,250,000","proofSize":"0"},"class":"Mandatory","paysFee":"Yes"}]}]}}},"16971989":{"convictionVoting":{"vote":{"index":0,"signer":"H52wVBJVjfRvqfq1wimsYNLFPqpiBDXLBy4i9ozCFzj7YMx","args":["117","{\"standard\":{\"vote\":\"0x00\",\"balance\":0}}"],"events":[{"section":"system","method":"ExtrinsicSuccess","data":[{"weight":{"refTime":"255,250,000","proofSize":"0"},"class":"Mandatory","paysFee":"Yes"}]}]}}},"16972069":{"convictionVoting":{"vote":{"index":0,"signer":"FJcnsNkMjY8tgJrDVeq5CKoB1b4Au2xGQjaMv8Ax5QAiV6p","args":["122","{\"standard\":{\"vote\":\"0x81\",\"balance\":10000000000000}}"],"events":[{"section":"system","method":"ExtrinsicSuccess","data":[{"weight":{"refTime":"255,250,000","proofSize":"0"},"class":"Mandatory","paysFee":"Yes"}]}]}}},"16972118":{"convictionVoting":{"vote":{"index":0,"signer":"Di33zuZw5LxLUhg5JU7bLuPrhn1R921su51LabLyYPhM2MP","args":["122","{\"standard\":{\"vote\":\"0x81\",\"balance\":10000000000000}}"],"events":[{"section":"system","method":"ExtrinsicSuccess","data":[{"weight":{"refTime":"255,250,000","proofSize":"0"},"class":"Mandatory","paysFee":"Yes"}]}]}}},"16972122":{"convictionVoting":{"vote":{"index":0,"signer":"H6dMn25SiAcdKujQnTuUvg4fPsWUDZrw6Wt5jteuGxbtwoD","args":["122","{\"standard\":{\"vote\":\"0x81\",\"balance\":10000000000000}}"],"events":[{"section":"system","method":"ExtrinsicSuccess","data":[{"weight":{"refTime":"255,250,000","proofSize":"0"},"class":"Mandatory","paysFee":"Yes"}]}]}}},"16972138":{"convictionVoting":{"vote":{"index":0,"signer":"FqY3mdSf8ZxcBVvjzkbBLgP3XLbA2ikPrExtiWFpidkjPct","args":["122","{\"standard\":{\"vote\":\"0x81\",\"balance\":10000000000000}}"],"events":[{"section":"system","method":"ExtrinsicSuccess","data":[{"weight":{"refTime":"255,250,000","proofSize":"0"},"class":"Mandatory","paysFee":"Yes"}]}]}}},"16972141":{"convictionVoting":{"vote":{"index":0,"signer":"DpEBgXSmcUG6nbbCnS6pk4Nd9fvkoG4axBiw4EqJPQkqr3V","args":["122","{\"standard\":{\"vote\":\"0x81\",\"balance\":55160800000000}}"],"events":[{"section":"system","method":"ExtrinsicSuccess","data":[{"weight":{"refTime":"255,250,000","proofSize":"0"},"class":"Mandatory","paysFee":"Yes"}]}]}}},"16972464":{"convictionVoting":{"vote":{"index":0,"signer":"FCUvpYbs2H7Dch98wenjHxDYkjn4DiSV3MQuryARPjpWfHd","args":["122","{\"standard\":{\"vote\":\"0x81\",\"balance\":10000000000000}}"],"events":[{"section":"system","method":"ExtrinsicSuccess","data":[{"weight":{"refTime":"255,250,000","proofSize":"0"},"class":"Mandatory","paysFee":"Yes"}]}]}}},"16972465":{"convictionVoting":{"vote":{"index":0,"signer":"HU9ZyZqTJopohQWXsnFY8NZBNjNw17KYnzoxnHn8RtCz8ko","args":["122","{\"standard\":{\"vote\":\"0x81\",\"balance\":10000000000000}}"],"events":[{"section":"system","method":"ExtrinsicSuccess","data":[{"weight":{"refTime":"255,250,000","proofSize":"0"},"class":"Mandatory","paysFee":"Yes"}]}]}}},"16972473":{"convictionVoting":{"vote":{"index":0,"signer":"JHUdcxgy5dhLFu8wXmskpSLnrXH1ue9rYG7oQFUDPqxzX3u","args":["122","{\"standard\":{\"vote\":\"0x81\",\"balance\":18105200000000}}"],"events":[{"section":"system","method":"ExtrinsicSuccess","data":[{"weight":{"refTime":"255,250,000","proofSize":"0"},"class":"Mandatory","paysFee":"Yes"}]}]}}},"16972475":{"convictionVoting":{"vote":{"index":0,"signer":"G4cQFMqRpWSzkNKxM2Uk6AVEShK2vCSWg7BWM34WZLw8dYn","args":["122","{\"standard\":{\"vote\":\"0x81\",\"balance\":12681700000000}}"],"events":[{"section":"system","method":"ExtrinsicSuccess","data":[{"weight":{"refTime":"255,250,000","proofSize":"0"},"class":"Mandatory","paysFee":"Yes"}]}]}}},"16972479":{"convictionVoting":{"vote":{"index":0,"signer":"FLMHZJ2arv1K6Cz9E7j5PJcxLvR2AmD5QsRk6kG4XdFxsz5","args":["122","{\"standard\":{\"vote\":\"0x81\",\"balance\":10000000000000}}"],"events":[{"section":"system","method":"ExtrinsicSuccess","data":[{"weight":{"refTime":"255,250,000","proofSize":"0"},"class":"Mandatory","paysFee":"Yes"}]}]}}},"16972482":{"convictionVoting":{"vote":{"index":0,"signer":"JCHVzJjBWS1ZxkTZJN1jifYrDcspepCU2YCW23XhtVQnYE7","args":["122","{\"standard\":{\"vote\":\"0x81\",\"balance\":11000000000000}}"],"events":[{"section":"system","method":"ExtrinsicSuccess","data":[{"weight":{"refTime":"255,250,000","proofSize":"0"},"class":"Mandatory","paysFee":"Yes"}]}]}}},"16972529":{"convictionVoting":{"vote":{"index":0,"signer":"HHHyHUy3kKpWQt2o47NdDxHAPHg6rXMHsAZjCSbS5rvpStY","args":["122","{\"standard\":{\"vote\":\"0x81\",\"balance\":10650000000000}}"],"events":[{"section":"system","method":"ExtrinsicSuccess","data":[{"weight":{"refTime":"255,250,000","proofSize":"0"},"class":"Mandatory","paysFee":"Yes"}]}]}}},"16972531":{"convictionVoting":{"vote":{"index":0,"signer":"DGm5ntY1Cifr427BKhFXtVyCgxEW7cbg7xqX7Y8pEYaGt3c","args":["122","{\"standard\":{\"vote\":\"0x81\",\"balance\":10000000000000}}"],"events":[{"section":"system","method":"ExtrinsicSuccess","data":[{"weight":{"refTime":"255,250,000","proofSize":"0"},"class":"Mandatory","paysFee":"Yes"}]}]}}},"16972755":{"convictionVoting":{"vote":{"index":0,"signer":"DG8Q1VmFkmDwuKDN9ZqdB78W6BiXTX5Z33XzZNAykuB5nFh","args":["115","{\"standard\":{\"vote\":\"0x81\",\"balance\":150180000000000}}"],"events":[{"section":"system","method":"ExtrinsicSuccess","data":[{"weight":{"refTime":"255,250,000","proofSize":"0"},"class":"Mandatory","paysFee":"Yes"}]}]}}},"16973072":{"convictionVoting":{"vote":{"index":0,"signer":"HWyLYmpW68JGJYoVJcot6JQ1CJbtUQeTdxfY1kUTsvGCB1r","args":["122","{\"standard\":{\"vote\":\"0x86\",\"balance\":111000000000000}}"],"events":[{"section":"system","method":"ExtrinsicSuccess","data":[{"weight":{"refTime":"255,250,000","proofSize":"0"},"class":"Mandatory","paysFee":"Yes"}]}]}}},"16973313":{"convictionVoting":{"vote":{"index":0,"signer":"HtSKUKWRPCxCtzsnNfdbN1NN5uVq4yMizb2FqeHSC3YoRTi","args":["122","{\"standard\":{\"vote\":\"0x81\",\"balance\":10000000000000}}"],"events":[{"section":"system","method":"ExtrinsicSuccess","data":[{"weight":{"refTime":"255,250,000","proofSize":"0"},"class":"Mandatory","paysFee":"Yes"}]}]}}},"16973369":{"convictionVoting":{"vote":{"index":0,"signer":"EBCKue3wpJY6BNTDp7Vo3yveCr19TxHmNPtYLuyv29uTXjU","args":["118","{\"standard\":{\"vote\":\"0x81\",\"balance\":499900000000}}"],"events":[{"section":"system","method":"ExtrinsicSuccess","data":[{"weight":{"refTime":"255,250,000","proofSize":"0"},"class":"Mandatory","paysFee":"Yes"}]}]}}},"16973390":{"convictionVoting":{"vote":{"index":0,"signer":"EBCKue3wpJY6BNTDp7Vo3yveCr19TxHmNPtYLuyv29uTXjU","args":["119","{\"standard\":{\"vote\":\"0x81\",\"balance\":499900000000}}"],"events":[{"section":"system","method":"ExtrinsicSuccess","data":[{"weight":{"refTime":"255,250,000","proofSize":"0"},"class":"Mandatory","paysFee":"Yes"}]}]}}},"16973394":{"convictionVoting":{"vote":{"index":0,"signer":"EBCKue3wpJY6BNTDp7Vo3yveCr19TxHmNPtYLuyv29uTXjU","args":["120","{\"standard\":{\"vote\":\"0x01\",\"balance\":499900000000}}"],"events":[{"section":"system","method":"ExtrinsicSuccess","data":[{"weight":{"refTime":"255,250,000","proofSize":"0"},"class":"Mandatory","paysFee":"Yes"}]}]}}},"16973413":{"convictionVoting":{"vote":{"index":0,"signer":"EBCKue3wpJY6BNTDp7Vo3yveCr19TxHmNPtYLuyv29uTXjU","args":["121","{\"standard\":{\"vote\":\"0x81\",\"balance\":499900000000}}"],"events":[{"section":"system","method":"ExtrinsicSuccess","data":[{"weight":{"refTime":"255,250,000","proofSize":"0"},"class":"Mandatory","paysFee":"Yes"}]}]}}},"16973422":{"convictionVoting":{"vote":{"index":0,"signer":"EBCKue3wpJY6BNTDp7Vo3yveCr19TxHmNPtYLuyv29uTXjU","args":["122","{\"standard\":{\"vote\":\"0x81\",\"balance\":499900000000}}"],"events":[{"section":"system","method":"ExtrinsicSuccess","data":[{"weight":{"refTime":"255,250,000","proofSize":"0"},"class":"Mandatory","paysFee":"Yes"}]}]}}},"16973491":{"convictionVoting":{"vote":{"index":0,"signer":"H2YnkDC3A5Wqtou7r8avQzs83bycbp3CHqNX4dtWbErjcBu","args":["109","{\"standard\":{\"vote\":\"0x82\",\"balance\":1600000000000}}"],"events":[{"section":"system","method":"ExtrinsicSuccess","data":[{"weight":{"refTime":"255,250,000","proofSize":"0"},"class":"Mandatory","paysFee":"Yes"}]}]}}},"16973499":{"convictionVoting":{"vote":{"index":0,"signer":"H2YnkDC3A5Wqtou7r8avQzs83bycbp3CHqNX4dtWbErjcBu","args":["111","{\"standard\":{\"vote\":\"0x82\",\"balance\":1600000000000}}"],"events":[{"section":"system","method":"ExtrinsicSuccess","data":[{"weight":{"refTime":"255,250,000","proofSize":"0"},"class":"Mandatory","paysFee":"Yes"}]}]}}},"16973507":{"convictionVoting":{"vote":{"index":0,"signer":"H2YnkDC3A5Wqtou7r8avQzs83bycbp3CHqNX4dtWbErjcBu","args":["112","{\"standard\":{\"vote\":\"0x02\",\"balance\":1600000000000}}"],"events":[{"section":"system","method":"ExtrinsicSuccess","data":[{"weight":{"refTime":"255,250,000","proofSize":"0"},"class":"Mandatory","paysFee":"Yes"}]}]}}},"16973515":{"convictionVoting":{"vote":{"index":0,"signer":"H2YnkDC3A5Wqtou7r8avQzs83bycbp3CHqNX4dtWbErjcBu","args":["113","{\"standard\":{\"vote\":\"0x02\",\"balance\":1600000000000}}"],"events":[{"section":"system","method":"ExtrinsicSuccess","data":[{"weight":{"refTime":"255,250,000","proofSize":"0"},"class":"Mandatory","paysFee":"Yes"}]}]}}},"16973526":{"convictionVoting":{"vote":{"index":0,"signer":"H2YnkDC3A5Wqtou7r8avQzs83bycbp3CHqNX4dtWbErjcBu","args":["115","{\"standard\":{\"vote\":\"0x82\",\"balance\":1600000000000}}"],"events":[{"section":"system","method":"ExtrinsicSuccess","data":[{"weight":{"refTime":"255,250,000","proofSize":"0"},"class":"Mandatory","paysFee":"Yes"}]}]}}},"16973535":{"convictionVoting":{"vote":{"index":0,"signer":"H2YnkDC3A5Wqtou7r8avQzs83bycbp3CHqNX4dtWbErjcBu","args":["116","{\"standard\":{\"vote\":\"0x02\",\"balance\":1600000000000}}"],"events":[{"section":"system","method":"ExtrinsicSuccess","data":[{"weight":{"refTime":"255,250,000","proofSize":"0"},"class":"Mandatory","paysFee":"Yes"}]}]}}},"16973541":{"convictionVoting":{"vote":{"index":0,"signer":"H2YnkDC3A5Wqtou7r8avQzs83bycbp3CHqNX4dtWbErjcBu","args":["117","{\"standard\":{\"vote\":\"0x02\",\"balance\":1600000000000}}"],"events":[{"section":"system","method":"ExtrinsicSuccess","data":[{"weight":{"refTime":"255,250,000","proofSize":"0"},"class":"Mandatory","paysFee":"Yes"}]}]}}},"16973548":{"convictionVoting":{"vote":{"index":0,"signer":"H2YnkDC3A5Wqtou7r8avQzs83bycbp3CHqNX4dtWbErjcBu","args":["118","{\"standard\":{\"vote\":\"0x82\",\"balance\":1600000000000}}"],"events":[{"section":"system","method":"ExtrinsicSuccess","data":[{"weight":{"refTime":"255,250,000","proofSize":"0"},"class":"Mandatory","paysFee":"Yes"}]}]}}},"16973664":{"convictionVoting":{"vote":{"index":0,"signer":"GkR4gRvFXCTErUAFoQQUF5VWPF13HopwywxdWXCoxwrpSZk","args":["122","{\"standard\":{\"vote\":\"0x81\",\"balance\":11000000000000}}"],"events":[{"section":"system","method":"ExtrinsicSuccess","data":[{"weight":{"refTime":"255,250,000","proofSize":"0"},"class":"Mandatory","paysFee":"Yes"}]}]}}},"16973669":{"convictionVoting":{"vote":{"index":0,"signer":"GkR4gRvFXCTErUAFoQQUF5VWPF13HopwywxdWXCoxwrpSZk","args":["118","{\"standard\":{\"vote\":\"0x81\",\"balance\":11000000000000}}"],"events":[{"section":"system","method":"ExtrinsicSuccess","data":[{"weight":{"refTime":"255,250,000","proofSize":"0"},"class":"Mandatory","paysFee":"Yes"}]}]}}},"16973672":{"convictionVoting":{"vote":{"index":0,"signer":"GkR4gRvFXCTErUAFoQQUF5VWPF13HopwywxdWXCoxwrpSZk","args":["117","{\"standard\":{\"vote\":\"0x01\",\"balance\":11000000000000}}"],"events":[{"section":"system","method":"ExtrinsicSuccess","data":[{"weight":{"refTime":"255,250,000","proofSize":"0"},"class":"Mandatory","paysFee":"Yes"}]}]}}},"16973678":{"convictionVoting":{"vote":{"index":0,"signer":"GkR4gRvFXCTErUAFoQQUF5VWPF13HopwywxdWXCoxwrpSZk","args":["119","{\"standard\":{\"vote\":\"0x01\",\"balance\":11000000000000}}"],"events":[{"section":"system","method":"ExtrinsicSuccess","data":[{"weight":{"refTime":"255,250,000","proofSize":"0"},"class":"Mandatory","paysFee":"Yes"}]}]}}},"16973681":{"convictionVoting":{"vote":{"index":0,"signer":"GkR4gRvFXCTErUAFoQQUF5VWPF13HopwywxdWXCoxwrpSZk","args":["121","{\"standard\":{\"vote\":\"0x01\",\"balance\":11000000000000}}"],"events":[{"section":"system","method":"ExtrinsicSuccess","data":[{"weight":{"refTime":"255,250,000","proofSize":"0"},"class":"Mandatory","paysFee":"Yes"}]}]}}},"16973684":{"convictionVoting":{"vote":{"index":0,"signer":"GkR4gRvFXCTErUAFoQQUF5VWPF13HopwywxdWXCoxwrpSZk","args":["120","{\"standard\":{\"vote\":\"0x01\",\"balance\":11000000000000}}"],"events":[{"section":"system","method":"ExtrinsicSuccess","data":[{"weight":{"refTime":"255,250,000","proofSize":"0"},"class":"Mandatory","paysFee":"Yes"}]}]}}},"16973858":{"convictionVoting":{"vote":{"index":0,"signer":"JFArxqV6rqPSwBok3zQDnj5jL6vwsZQDwYXXqb1cFygnYVt","args":["122","{\"standard\":{\"vote\":\"0x81\",\"balance\":100000000000000}}"],"events":[{"section":"system","method":"ExtrinsicSuccess","data":[{"weight":{"refTime":"255,250,000","proofSize":"0"},"class":"Mandatory","paysFee":"Yes"}]}]}}},"16973907":{"convictionVoting":{"vote":{"index":0,"signer":"GPXThfrRtVwyLu5q788nq9zUiKVRHwX4z6quSdN2vRg1Ww4","args":["122","{\"standard\":{\"vote\":\"0x81\",\"balance\":10100000000000}}"],"events":[{"section":"system","method":"ExtrinsicSuccess","data":[{"weight":{"refTime":"255,250,000","proofSize":"0"},"class":"Mandatory","paysFee":"Yes"}]}]}}},"16973908":{"convictionVoting":{"vote":{"index":0,"signer":"DDuHcFtsAaJyk3RxXJGybN3icx95TouqLYF5jjb1Uqnvwtg","args":["122","{\"standard\":{\"vote\":\"0x81\",\"balance\":10000000000000}}"],"events":[{"section":"system","method":"ExtrinsicSuccess","data":[{"weight":{"refTime":"255,250,000","proofSize":"0"},"class":"Mandatory","paysFee":"Yes"}]}]}}},"16973913":{"convictionVoting":{"vote":{"index":0,"signer":"FtbEoFRHt2K8kFBwVZsJzwmwEF5rnC5ZvwCphTe64fGUAk4","args":["122","{\"standard\":{\"vote\":\"0x81\",\"balance\":10000000000000}}"],"events":[{"section":"system","method":"ExtrinsicSuccess","data":[{"weight":{"refTime":"255,250,000","proofSize":"0"},"class":"Mandatory","paysFee":"Yes"}]}]}}},"16973916":{"convictionVoting":{"vote":{"index":0,"signer":"EVgkDV9X4BmnMi3ZNgrkKW3WEiaZ6wqE1HVRZziNnERmyfi","args":["122","{\"standard\":{\"vote\":\"0x81\",\"balance\":11000000000000}}"],"events":[{"section":"system","method":"ExtrinsicSuccess","data":[{"weight":{"refTime":"255,250,000","proofSize":"0"},"class":"Mandatory","paysFee":"Yes"}]}]}}},"16973976":{"convictionVoting":{"vote":{"index":0,"signer":"FFvhijZofjqZEXwE2hvpKHbyNDexDHq3Qk1ti7SaCmYTRF5","args":["122","{\"standard\":{\"vote\":\"0x81\",\"balance\":10000000000000}}"],"events":[{"section":"system","method":"ExtrinsicSuccess","data":[{"weight":{"refTime":"255,250,000","proofSize":"0"},"class":"Mandatory","paysFee":"Yes"}]}]}}},"16973978":{"convictionVoting":{"vote":{"index":0,"signer":"HUE5nUANxvCRW7SoLAHcKdB2PLoUpUVyuSdviHrKKQAV5EC","args":["122","{\"standard\":{\"vote\":\"0x81\",\"balance\":10000000000000}}"],"events":[{"section":"system","method":"ExtrinsicSuccess","data":[{"weight":{"refTime":"255,250,000","proofSize":"0"},"class":"Mandatory","paysFee":"Yes"}]}]}}},"16973984":{"convictionVoting":{"vote":{"index":0,"signer":"FUyY55mx5zavpkETx3Na9wi421eJ7rhijoRmXWNCBHUik8Q","args":["122","{\"splitAbstain\":{\"aye\":0,\"nay\":0,\"abstain\":10648700000000}}"],"events":[{"section":"system","method":"ExtrinsicSuccess","data":[{"weight":{"refTime":"255,250,000","proofSize":"0"},"class":"Mandatory","paysFee":"Yes"}]}]}}},"16973986":{"convictionVoting":{"vote":{"index":0,"signer":"HRvhZa1T6WwApvJrjiiqLf3W5WfjggoU9664pWxEpYNcXdS","args":["122","{\"standard\":{\"vote\":\"0x81\",\"balance\":10000000000000}}"],"events":[{"section":"system","method":"ExtrinsicSuccess","data":[{"weight":{"refTime":"255,250,000","proofSize":"0"},"class":"Mandatory","paysFee":"Yes"}]}]}}},"16974142":{"convictionVoting":{"vote":{"index":0,"signer":"J19UsjSRFtULA22b8gzDUpUkVEVEdg8wm61by6oictraL9g","args":["122","{\"standard\":{\"vote\":\"0x81\",\"balance\":90000000000}}"],"events":[{"section":"system","method":"ExtrinsicSuccess","data":[{"weight":{"refTime":"255,250,000","proofSize":"0"},"class":"Mandatory","paysFee":"Yes"}]}]}}},"16974145":{"convictionVoting":{"vote":{"index":0,"signer":"FndpA4bc82CDtiRMaGZQJmEum8m9JzZuQnxPfMKiykDUcN6","args":["122","{\"standard\":{\"vote\":\"0x81\",\"balance\":100000000000}}"],"events":[{"section":"system","method":"ExtrinsicSuccess","data":[{"weight":{"refTime":"255,250,000","proofSize":"0"},"class":"Mandatory","paysFee":"Yes"}]}]}}},"16974148":{"convictionVoting":{"vote":{"index":0,"signer":"FPnWvBdT2DmXo3jHVqgvTgKUnWBqc9riuoS4Fcct7DK1rS5","args":["122","{\"standard\":{\"vote\":\"0x81\",\"balance\":500000000000}}"],"events":[{"section":"system","method":"ExtrinsicSuccess","data":[{"weight":{"refTime":"255,250,000","proofSize":"0"},"class":"Mandatory","paysFee":"Yes"}]}]}}},"16974151":{"convictionVoting":{"vote":{"index":0,"signer":"DG7cxb3rnFEhgFxvax4FMf5EVDCT2iZgGR2sKXciw3KFUzf","args":["122","{\"standard\":{\"vote\":\"0x81\",\"balance\":500000000000}}"],"events":[{"section":"system","method":"ExtrinsicSuccess","data":[{"weight":{"refTime":"255,250,000","proofSize":"0"},"class":"Mandatory","paysFee":"Yes"}]}]}}},"16974153":{"convictionVoting":{"vote":{"index":0,"signer":"DQQJLG14UMDaaotKEVijFj9UngZuS8AwJxbGQ2z5Ah3zn4B","args":["122","{\"standard\":{\"vote\":\"0x81\",\"balance\":200000000000}}"],"events":[{"section":"system","method":"ExtrinsicSuccess","data":[{"weight":{"refTime":"255,250,000","proofSize":"0"},"class":"Mandatory","paysFee":"Yes"}]}]}}},"16974156":{"convictionVoting":{"vote":{"index":0,"signer":"DV8mbVPenHC5JrpWqAjkTXQRAnMDyFk2SzoxKWqRnrXkqed","args":["122","{\"standard\":{\"vote\":\"0x81\",\"balance\":100000000000}}"],"events":[{"section":"system","method":"ExtrinsicSuccess","data":[{"weight":{"refTime":"255,250,000","proofSize":"0"},"class":"Mandatory","paysFee":"Yes"}]}]}}},"16974160":{"convictionVoting":{"vote":{"index":0,"signer":"G2C5EyyUhKPXcDNZBbd2KgFS9RzEPazt4uT6pZ2oC9Pj5fK","args":["122","{\"standard\":{\"vote\":\"0x81\",\"balance\":70000000000}}"],"events":[{"section":"system","method":"ExtrinsicSuccess","data":[{"weight":{"refTime":"255,250,000","proofSize":"0"},"class":"Mandatory","paysFee":"Yes"}]}]}}},"16974198":{"convictionVoting":{"vote":{"index":0,"signer":"GFCnULt6joMQEMM1yHuGQZCZpxw7kVKu3XkFZxcdxGbF3pu","args":["117","{\"standard\":{\"vote\":\"0x81\",\"balance\":0}}"],"events":[{"section":"system","method":"ExtrinsicSuccess","data":[{"weight":{"refTime":"255,250,000","proofSize":"0"},"class":"Mandatory","paysFee":"Yes"}]}]}}},"16974199":{"convictionVoting":{"vote":{"index":0,"signer":"GFCnULt6joMQEMM1yHuGQZCZpxw7kVKu3XkFZxcdxGbF3pu","args":["118","{\"standard\":{\"vote\":\"0x81\",\"balance\":1000000000000}}"],"events":[{"section":"system","method":"ExtrinsicSuccess","data":[{"weight":{"refTime":"255,250,000","proofSize":"0"},"class":"Mandatory","paysFee":"Yes"}]}]}}},"16974201":{"convictionVoting":{"vote":{"index":0,"signer":"GFCnULt6joMQEMM1yHuGQZCZpxw7kVKu3XkFZxcdxGbF3pu","args":["119","{\"standard\":{\"vote\":\"0x81\",\"balance\":1000000000000}}"],"events":[{"section":"system","method":"ExtrinsicSuccess","data":[{"weight":{"refTime":"255,250,000","proofSize":"0"},"class":"Mandatory","paysFee":"Yes"}]}]}}},"16974202":{"convictionVoting":{"vote":{"index":0,"signer":"GFCnULt6joMQEMM1yHuGQZCZpxw7kVKu3XkFZxcdxGbF3pu","args":["120","{\"standard\":{\"vote\":\"0x81\",\"balance\":1000000000000}}"],"events":[{"section":"system","method":"ExtrinsicSuccess","data":[{"weight":{"refTime":"255,250,000","proofSize":"0"},"class":"Mandatory","paysFee":"Yes"}]}]}}},"16974203":{"convictionVoting":{"vote":{"index":0,"signer":"GFCnULt6joMQEMM1yHuGQZCZpxw7kVKu3XkFZxcdxGbF3pu","args":["122","{\"standard\":{\"vote\":\"0x81\",\"balance\":1000000000000}}"],"events":[{"section":"system","method":"ExtrinsicSuccess","data":[{"weight":{"refTime":"255,250,000","proofSize":"0"},"class":"Mandatory","paysFee":"Yes"}]}]}}},"16974205":{"convictionVoting":{"vote":{"index":0,"signer":"GFCnULt6joMQEMM1yHuGQZCZpxw7kVKu3XkFZxcdxGbF3pu","args":["121","{\"standard\":{\"vote\":\"0x81\",\"balance\":1000000000000}}"],"events":[{"section":"system","method":"ExtrinsicSuccess","data":[{"weight":{"refTime":"255,250,000","proofSize":"0"},"class":"Mandatory","paysFee":"Yes"}]}]}}},"16974214":{"convictionVoting":{"vote":{"index":0,"signer":"GFCnULt6joMQEMM1yHuGQZCZpxw7kVKu3XkFZxcdxGbF3pu","args":["115","{\"standard\":{\"vote\":\"0x81\",\"balance\":1000000000000}}"],"events":[{"section":"system","method":"ExtrinsicSuccess","data":[{"weight":{"refTime":"255,250,000","proofSize":"0"},"class":"Mandatory","paysFee":"Yes"}]}]}}},"16974215":{"convictionVoting":{"vote":{"index":0,"signer":"GFCnULt6joMQEMM1yHuGQZCZpxw7kVKu3XkFZxcdxGbF3pu","args":["116","{\"standard\":{\"vote\":\"0x81\",\"balance\":1000000000000}}"],"events":[{"section":"system","method":"ExtrinsicSuccess","data":[{"weight":{"refTime":"255,250,000","proofSize":"0"},"class":"Mandatory","paysFee":"Yes"}]}]}}},"16974216":{"convictionVoting":{"vote":{"index":0,"signer":"GFCnULt6joMQEMM1yHuGQZCZpxw7kVKu3XkFZxcdxGbF3pu","args":["119","{\"standard\":{\"vote\":\"0x81\",\"balance\":1000000000000}}"],"events":[{"section":"system","method":"ExtrinsicSuccess","data":[{"weight":{"refTime":"255,250,000","proofSize":"0"},"class":"Mandatory","paysFee":"Yes"}]}]}}},"16974218":{"convictionVoting":{"vote":{"index":1,"signer":"GFCnULt6joMQEMM1yHuGQZCZpxw7kVKu3XkFZxcdxGbF3pu","args":["118","{\"standard\":{\"vote\":\"0x81\",\"balance\":1000000000000}}"],"events":[{"section":"system","method":"ExtrinsicSuccess","data":[{"weight":{"refTime":"603,134,249,155","proofSize":"0"},"class":"Mandatory","paysFee":"Yes"}]}]}}},"16974246":{"convictionVoting":{"vote":{"index":0,"signer":"Hf8C626KBAjitMV7w8AhQWDCiPgUU47htEwbomq5mDMKeyL","args":["120","{\"standard\":{\"vote\":\"0x06\",\"balance\":111000000000000}}"],"events":[{"section":"system","method":"ExtrinsicSuccess","data":[{"weight":{"refTime":"255,250,000","proofSize":"0"},"class":"Mandatory","paysFee":"Yes"}]}]}}},"16974251":{"convictionVoting":{"vote":{"index":0,"signer":"Hf8C626KBAjitMV7w8AhQWDCiPgUU47htEwbomq5mDMKeyL","args":["122","{\"standard\":{\"vote\":\"0x86\",\"balance\":111000000000000}}"],"events":[{"section":"system","method":"ExtrinsicSuccess","data":[{"weight":{"refTime":"255,250,000","proofSize":"0"},"class":"Mandatory","paysFee":"Yes"}]}]}}},"16974253":{"convictionVoting":{"vote":{"index":0,"signer":"Hf8C626KBAjitMV7w8AhQWDCiPgUU47htEwbomq5mDMKeyL","args":["121","{\"standard\":{\"vote\":\"0x86\",\"balance\":111000000000000}}"],"events":[{"section":"system","method":"ExtrinsicSuccess","data":[{"weight":{"refTime":"255,250,000","proofSize":"0"},"class":"Mandatory","paysFee":"Yes"}]}]}}},"16974466":{"convictionVoting":{"vote":{"index":0,"signer":"HLfUw3p1W5mx57wJeDG6n6uRYDR7H22ViRLuCTgbJCirbai","args":["122","{\"standard\":{\"vote\":\"0x80\",\"balance\":3000000000000}}"],"events":[{"section":"system","method":"ExtrinsicSuccess","data":[{"weight":{"refTime":"255,250,000","proofSize":"0"},"class":"Mandatory","paysFee":"Yes"}]}]}}},"16974469":{"convictionVoting":{"vote":{"index":0,"signer":"DPb2z99bbieLXWADo1dsLTijTc84vktx5nZmu79NztbC3NS","args":["122","{\"standard\":{\"vote\":\"0x80\",\"balance\":3000000000000}}"],"events":[{"section":"system","method":"ExtrinsicSuccess","data":[{"weight":{"refTime":"255,250,000","proofSize":"0"},"class":"Mandatory","paysFee":"Yes"}]}]}}},"16974528":{"convictionVoting":{"vote":{"index":0,"signer":"FqoPGAqaZWBWAmKTX7mAToCv8aV3mqqgxiSNE9kKRLWuEC7","args":["122","{\"standard\":{\"vote\":\"0x81\",\"balance\":10000000000000}}"],"events":[{"section":"system","method":"ExtrinsicSuccess","data":[{"weight":{"refTime":"255,250,000","proofSize":"0"},"class":"Mandatory","paysFee":"Yes"}]}]}}},"16974536":{"convictionVoting":{"vote":{"index":0,"signer":"DPuG89deqMcPAbPBYsbonzFrMAzZgTmBxmMNuH5LiQxcu7X","args":["122","{\"standard\":{\"vote\":\"0x81\",\"balance\":11000000000000}}"],"events":[{"section":"system","method":"ExtrinsicSuccess","data":[{"weight":{"refTime":"255,250,000","proofSize":"0"},"class":"Mandatory","paysFee":"Yes"}]}]}}},"16974540":{"convictionVoting":{"vote":{"index":0,"signer":"FqoPGAqaZWBWAmKTX7mAToCv8aV3mqqgxiSNE9kKRLWuEC7","args":["122","{\"standard\":{\"vote\":\"0x81\",\"balance\":10000000000000}}"],"events":[{"section":"system","method":"ExtrinsicSuccess","data":[{"weight":{"refTime":"255,250,000","proofSize":"0"},"class":"Mandatory","paysFee":"Yes"}]}]}}},"16974614":{"convictionVoting":{"vote":{"index":0,"signer":"Dom3VWEQu8JNePDhX3Ce581eVLK77rSdBbqDLtRb5ZWHV31","args":["122","{\"standard\":{\"vote\":\"0x81\",\"balance\":5000000000000}}"],"events":[{"section":"system","method":"ExtrinsicSuccess","data":[{"weight":{"refTime":"255,250,000","proofSize":"0"},"class":"Mandatory","paysFee":"Yes"}]}]}}},"16974617":{"convictionVoting":{"vote":{"index":0,"signer":"Dom3VWEQu8JNePDhX3Ce581eVLK77rSdBbqDLtRb5ZWHV31","args":["114","{\"standard\":{\"vote\":\"0x01\",\"balance\":5000000000000}}"],"events":[{"section":"system","method":"ExtrinsicSuccess","data":[{"weight":{"refTime":"255,250,000","proofSize":"0"},"class":"Mandatory","paysFee":"Yes"}]}]}}},"16974620":{"convictionVoting":{"vote":{"index":0,"signer":"Dom3VWEQu8JNePDhX3Ce581eVLK77rSdBbqDLtRb5ZWHV31","args":["118","{\"standard\":{\"vote\":\"0x81\",\"balance\":5000000000000}}"],"events":[{"section":"system","method":"ExtrinsicSuccess","data":[{"weight":{"refTime":"255,250,000","proofSize":"0"},"class":"Mandatory","paysFee":"Yes"}]}]}}},"16974626":{"convictionVoting":{"vote":{"index":0,"signer":"Dom3VWEQu8JNePDhX3Ce581eVLK77rSdBbqDLtRb5ZWHV31","args":["118","{\"standard\":{\"vote\":\"0x81\",\"balance\":5000000000000}}"],"events":[{"section":"system","method":"ExtrinsicSuccess","data":[{"weight":{"refTime":"255,250,000","proofSize":"0"},"class":"Mandatory","paysFee":"Yes"}]}]}}},"16974629":{"convictionVoting":{"vote":{"index":0,"signer":"Dom3VWEQu8JNePDhX3Ce581eVLK77rSdBbqDLtRb5ZWHV31","args":["118","{\"standard\":{\"vote\":\"0x81\",\"balance\":5000000000000}}"],"events":[{"section":"system","method":"ExtrinsicSuccess","data":[{"weight":{"refTime":"255,250,000","proofSize":"0"},"class":"Mandatory","paysFee":"Yes"}]}]}}},"16974630":{"convictionVoting":{"vote":{"index":0,"signer":"Dom3VWEQu8JNePDhX3Ce581eVLK77rSdBbqDLtRb5ZWHV31","args":["120","{\"standard\":{\"vote\":\"0x01\",\"balance\":5000000000000}}"],"events":[{"section":"system","method":"ExtrinsicSuccess","data":[{"weight":{"refTime":"255,250,000","proofSize":"0"},"class":"Mandatory","paysFee":"Yes"}]}]}}},"16974669":{"convictionVoting":{"vote":{"index":0,"signer":"EVhWhw6w6i5C9SV3FbHdM1rroTxsM5UzxEKMyXCwnct2EnH","args":["122","{\"standard\":{\"vote\":\"0x80\",\"balance\":50000000000000}}"],"events":[{"section":"system","method":"ExtrinsicSuccess","data":[{"weight":{"refTime":"255,250,000","proofSize":"0"},"class":"Mandatory","paysFee":"Yes"}]}]}}},"16974712":{"convictionVoting":{"removeVote":{"index":0,"signer":"CwRRCj786DH5DoLjKVHPoJFPExgKSpuvmY6LmMJJKyiP59K","args":["","105"],"events":[{"section":"system","method":"ExtrinsicSuccess","data":[{"weight":{"refTime":"255,250,000","proofSize":"0"},"class":"Mandatory","paysFee":"Yes"}]}]}}},"16974726":{"convictionVoting":{"removeVote":{"index":0,"signer":"CwRRCj786DH5DoLjKVHPoJFPExgKSpuvmY6LmMJJKyiP59K","args":["33","105"],"events":[{"section":"system","method":"ExtrinsicSuccess","data":[{"weight":{"refTime":"255,250,000","proofSize":"0"},"class":"Mandatory","paysFee":"Yes"}]}]}}},"16974777":{"convictionVoting":{"vote":{"index":0,"signer":"GLxyY9cx27VkZNrf33zHURwLLa58jU8XZeg8HDWkNpX2JXS","args":["122","{\"standard\":{\"vote\":\"0x80\",\"balance\":60000000000000}}"],"events":[{"section":"system","method":"ExtrinsicSuccess","data":[{"weight":{"refTime":"255,250,000","proofSize":"0"},"class":"Mandatory","paysFee":"Yes"}]}]}}},"16974785":{"convictionVoting":{"vote":{"index":0,"signer":"Cw2HqJ6m2pXVDatzZq8wNdUWwWaCnYLeyTM24ft3JNdZ25E","args":["122","{\"standard\":{\"vote\":\"0x80\",\"balance\":60000000000000}}"],"events":[{"section":"system","method":"ExtrinsicSuccess","data":[{"weight":{"refTime":"255,250,000","proofSize":"0"},"class":"Mandatory","paysFee":"Yes"}]}]}}},"16974792":{"convictionVoting":{"vote":{"index":0,"signer":"EoYkgoLQn1GZrJLmqVMd6GhSJYWtYAtzg3fEcWH6nXjscqC","args":["122","{\"standard\":{\"vote\":\"0x81\",\"balance\":25000000000000}}"],"events":[{"section":"system","method":"ExtrinsicSuccess","data":[{"weight":{"refTime":"255,250,000","proofSize":"0"},"class":"Mandatory","paysFee":"Yes"}]}]}}},"16974794":{"convictionVoting":{"vote":{"index":0,"signer":"E2gCFEisQ3k4LmaJHBysj8f1SRoG6jCo5ffFdX9XidqsjDC","args":["122","{\"standard\":{\"vote\":\"0x81\",\"balance\":25000000000000}}"],"events":[{"section":"system","method":"ExtrinsicSuccess","data":[{"weight":{"refTime":"255,250,000","proofSize":"0"},"class":"Mandatory","paysFee":"Yes"}]}]}}},"16974919":{"convictionVoting":{"delegate":{"index":0,"signer":"EzB5K2DvePdcdDHBNUc48wKLMQc9CESaqCjS1f21wHvQLMv","args":["0","HqRcfhH8VXMhuCk5JXe28WMgDDuW9MVDVNofe1nnTcefVZn","None","10000000000"],"events":[{"section":"system","method":"ExtrinsicSuccess","data":[{"weight":{"refTime":"255,250,000","proofSize":"0"},"class":"Mandatory","paysFee":"Yes"}]}]}}},"16975300":{"convictionVoting":{"vote":{"index":0,"signer":"J4mt2MknXc8AsLHt5M6pzFD1odT9sZrufEHyCPjbm8FafJd","args":["122","{\"standard\":{\"vote\":\"0x80\",\"balance\":5000000000000}}"],"events":[{"section":"system","method":"ExtrinsicSuccess","data":[{"weight":{"refTime":"255,250,000","proofSize":"0"},"class":"Mandatory","paysFee":"Yes"}]}]}}},"16975301":{"convictionVoting":{"vote":{"index":0,"signer":"Drb5XkyGvm26ph6d1DE4wxbwqiUCKyVXpcThBUSHE4VxrB7","args":["122","{\"standard\":{\"vote\":\"0x80\",\"balance\":5000000000000}}"],"events":[{"section":"system","method":"ExtrinsicSuccess","data":[{"weight":{"refTime":"255,250,000","proofSize":"0"},"class":"Mandatory","paysFee":"Yes"}]}]}}},"16975352":{"convictionVoting":{"vote":{"index":0,"signer":"Cdhjt72TSezVDkUzdgyoSwXByfwQJjuXSYcDs5L8snyB8Yx","args":["122","{\"standard\":{\"vote\":\"0x80\",\"balance\":60000000000000}}"],"events":[{"section":"system","method":"ExtrinsicSuccess","data":[{"weight":{"refTime":"255,250,000","proofSize":"0"},"class":"Mandatory","paysFee":"Yes"}]}]}}},"16975355":{"convictionVoting":{"vote":{"index":0,"signer":"EfeoSg3WEZo5kp3BKfwhwwJkh4GdSaS9MjaeH2nKREDovzw","args":["122","{\"standard\":{\"vote\":\"0x80\",\"balance\":60000000000000}}"],"events":[{"section":"system","method":"ExtrinsicSuccess","data":[{"weight":{"refTime":"255,250,000","proofSize":"0"},"class":"Mandatory","paysFee":"Yes"}]}]}}},"16975358":{"convictionVoting":{"vote":{"index":0,"signer":"GHuTRo2jNiXZyc87dU9jRF5iASx1J9G4rgZLPgxxFpj6jD3","args":["122","{\"standard\":{\"vote\":\"0x81\",\"balance\":10100000000000}}"],"events":[{"section":"system","method":"ExtrinsicSuccess","data":[{"weight":{"refTime":"255,250,000","proofSize":"0"},"class":"Mandatory","paysFee":"Yes"}]}]}}},"16975450":{"convictionVoting":{"vote":{"index":0,"signer":"HhQifoEAuBYsFrf83pFvHo87voFDMzAY61123HddZ8EScDL","args":["122","{\"standard\":{\"vote\":\"0x81\",\"balance\":13741212530871}}"],"events":[{"section":"system","method":"ExtrinsicSuccess","data":[{"weight":{"refTime":"255,250,000","proofSize":"0"},"class":"Mandatory","paysFee":"Yes"}]}]}}},"16975529":{"convictionVoting":{"vote":{"index":0,"signer":"HtGGdhxk2CFYAa5hqzMXK4YLuxoX9sbAEaRAdKt3b84GGjE","args":["116","{\"standard\":{\"vote\":\"0x82\",\"balance\":1997000000000000}}"],"events":[{"section":"system","method":"ExtrinsicSuccess","data":[{"weight":{"refTime":"255,250,000","proofSize":"0"},"class":"Mandatory","paysFee":"Yes"}]}]}}},"16975571":{"convictionVoting":{"vote":{"index":0,"signer":"EPV1c7jjoCFPkWqTzTkbuT3oGRM8HkjbTVHeuvsyiAbB2aZ","args":["122","{\"standard\":{\"vote\":\"0x84\",\"balance\":64000000000000}}"],"events":[{"section":"system","method":"ExtrinsicSuccess","data":[{"weight":{"refTime":"255,250,000","proofSize":"0"},"class":"Mandatory","paysFee":"Yes"}]}]}}},"16975574":{"convictionVoting":{"vote":{"index":0,"signer":"EPV2HxrBnVB2n4p7Mb38A3BrzCyREWbzQ75cC9rkZhRYcRE","args":["122","{\"standard\":{\"vote\":\"0x84\",\"balance\":64000000000000}}"],"events":[{"section":"system","method":"ExtrinsicSuccess","data":[{"weight":{"refTime":"255,250,000","proofSize":"0"},"class":"Mandatory","paysFee":"Yes"}]}]}}},"16975966":{"convictionVoting":{"vote":{"index":0,"signer":"DksUmQVCiMrdW8ecZ78hW7iLmVWGrayo5bd3HaB6pwbbiSy","args":["122","{\"standard\":{\"vote\":\"0x82\",\"balance\":6000096077628}}"],"events":[{"section":"system","method":"ExtrinsicSuccess","data":[{"weight":{"refTime":"255,250,000","proofSize":"0"},"class":"Mandatory","paysFee":"Yes"}]}]}}},"16976313":{"convictionVoting":{"vote":{"index":0,"signer":"DYXC7TEyGUtNRtF2NqGK5EomBFMnsEkM9DBQm4gsYfjuPBt","args":["116","{\"standard\":{\"vote\":\"0x86\",\"balance\":9500000000000}}"],"events":[{"section":"system","method":"ExtrinsicSuccess","data":[{"weight":{"refTime":"255,250,000","proofSize":"0"},"class":"Mandatory","paysFee":"Yes"}]}]}}},"16977095":{"convictionVoting":{"vote":{"index":0,"signer":"CuYVkVbKQ8Bth4mn8kwFjg9K7U8iMRUs2TkEragJWpQZBRi","args":["109","{\"standard\":{\"vote\":\"0x81\",\"balance\":100000000000}}"],"events":[{"section":"system","method":"ExtrinsicSuccess","data":[{"weight":{"refTime":"255,250,000","proofSize":"0"},"class":"Mandatory","paysFee":"Yes"}]}]}}},"16977145":{"convictionVoting":{"vote":{"index":0,"signer":"CuYVkVbKQ8Bth4mn8kwFjg9K7U8iMRUs2TkEragJWpQZBRi","args":["111","{\"standard\":{\"vote\":\"0x80\",\"balance\":100000000000}}"],"events":[{"section":"system","method":"ExtrinsicSuccess","data":[{"weight":{"refTime":"255,250,000","proofSize":"0"},"class":"Mandatory","paysFee":"Yes"}]}]}}},"16977268":{"convictionVoting":{"vote":{"index":0,"signer":"Fi8s4pW6CwJnkLsRFhqTbg2t29ApEnMUMejUvZr1StF1UkV","args":["118","{\"standard\":{\"vote\":\"0x81\",\"balance\":8291500000000}}"],"events":[{"section":"system","method":"ExtrinsicSuccess","data":[{"weight":{"refTime":"255,250,000","proofSize":"0"},"class":"Mandatory","paysFee":"Yes"}]}]}}},"16977432":{"convictionVoting":{"vote":{"index":0,"signer":"EUWaPzJV9soamnUPSUcp76mEjQkLZj4nt659DvdVzRG9k6a","args":["122","{\"standard\":{\"vote\":\"0x80\",\"balance\":6000000000000}}"],"events":[{"section":"system","method":"ExtrinsicSuccess","data":[{"weight":{"refTime":"255,250,000","proofSize":"0"},"class":"Mandatory","paysFee":"Yes"}]}]}}},"16977434":{"convictionVoting":{"vote":{"index":0,"signer":"FPc6HXzVyCbsarcyLEN6UnHbhWxdUputwEe5saQxmMUj63X","args":["122","{\"standard\":{\"vote\":\"0x80\",\"balance\":7000000000000}}"],"events":[{"section":"system","method":"ExtrinsicSuccess","data":[{"weight":{"refTime":"255,250,000","proofSize":"0"},"class":"Mandatory","paysFee":"Yes"}]}]}}},"16977443":{"convictionVoting":{"vote":{"index":0,"signer":"EvoLanodoqDsgHb98Ymbu41uXXKfCPDKxeM6dXHyJ2JoVus","args":["116","{\"standard\":{\"vote\":\"0x86\",\"balance\":700000000000000}}"],"events":[{"section":"system","method":"ExtrinsicSuccess","data":[{"weight":{"refTime":"255,250,000","proofSize":"0"},"class":"Mandatory","paysFee":"Yes"}]}]}}},"16977461":{"convictionVoting":{"vote":{"index":0,"signer":"EAMbhBVW7SpJfH332uABbDNtsbNnaZBBXeGJwdfxkxkPm6o","args":["116","{\"standard\":{\"vote\":\"0x80\",\"balance\":2000000000000}}"],"events":[{"section":"system","method":"ExtrinsicSuccess","data":[{"weight":{"refTime":"255,250,000","proofSize":"0"},"class":"Mandatory","paysFee":"Yes"}]}]}}},"16977598":{"convictionVoting":{"vote":{"index":0,"signer":"GUukavjKxAdj4Cb77DiwyNNhCSZ6H4RaSiRqYo1uaYiSWcM","args":["122","{\"standard\":{\"vote\":\"0x81\",\"balance\":14441700000000}}"],"events":[{"section":"system","method":"ExtrinsicSuccess","data":[{"weight":{"refTime":"255,250,000","proofSize":"0"},"class":"Mandatory","paysFee":"Yes"}]}]}}},"16977600":{"convictionVoting":{"vote":{"index":0,"signer":"EmUEXGdgutDjhdTxnc3zqxGTahYTRsDzfBiAPx6zENcL4TD","args":["116","{\"standard\":{\"vote\":\"0x80\",\"balance\":3000000000000}}"],"events":[{"section":"system","method":"ExtrinsicSuccess","data":[{"weight":{"refTime":"255,250,000","proofSize":"0"},"class":"Mandatory","paysFee":"Yes"}]}]}}},"16977890":{"convictionVoting":{"vote":{"index":0,"signer":"FFRsm3haD645qfSVE1zfywYURWQ6z7YUAD4nad6Zw6qVxDk","args":["122","{\"standard\":{\"vote\":\"0x81\",\"balance\":30000000000000}}"],"events":[{"section":"system","method":"ExtrinsicSuccess","data":[{"weight":{"refTime":"255,250,000","proofSize":"0"},"class":"Mandatory","paysFee":"Yes"}]}]}}},"16978481":{"convictionVoting":{"vote":{"index":0,"signer":"DGJbNYwFvftuyK3BnoGY8RRsaPbaUk3tUFB7JRjGwf3GFwy","args":["115","{\"standard\":{\"vote\":\"0x80\",\"balance\":192000000000000}}"],"events":[{"section":"system","method":"ExtrinsicSuccess","data":[{"weight":{"refTime":"255,250,000","proofSize":"0"},"class":"Mandatory","paysFee":"Yes"}]}]}}},"16978485":{"convictionVoting":{"vote":{"index":0,"signer":"DGJbNYwFvftuyK3BnoGY8RRsaPbaUk3tUFB7JRjGwf3GFwy","args":["115","{\"standard\":{\"vote\":\"0x86\",\"balance\":192000000000000}}"],"events":[{"section":"system","method":"ExtrinsicSuccess","data":[{"weight":{"refTime":"255,250,000","proofSize":"0"},"class":"Mandatory","paysFee":"Yes"}]}]}}},"16979236":{"convictionVoting":{"vote":{"index":0,"signer":"J9ABr4JCLTVbFrZASCxVz5Sspi6LMdYwVNZWinpyidn13xE","args":["111","{\"standard\":{\"vote\":\"0x80\",\"balance\":5000000000000}}"],"events":[{"section":"system","method":"ExtrinsicSuccess","data":[{"weight":{"refTime":"255,250,000","proofSize":"0"},"class":"Mandatory","paysFee":"Yes"}]}]}}},"16979245":{"convictionVoting":{"vote":{"index":0,"signer":"J9ABr4JCLTVbFrZASCxVz5Sspi6LMdYwVNZWinpyidn13xE","args":["109","{\"standard\":{\"vote\":\"0x83\",\"balance\":5000000000000}}"],"events":[{"section":"system","method":"ExtrinsicSuccess","data":[{"weight":{"refTime":"255,250,000","proofSize":"0"},"class":"Mandatory","paysFee":"Yes"}]}]}}},"16979277":{"convictionVoting":{"vote":{"index":0,"signer":"J9ABr4JCLTVbFrZASCxVz5Sspi6LMdYwVNZWinpyidn13xE","args":["112","{\"standard\":{\"vote\":\"0x00\",\"balance\":100000000000}}"],"events":[{"section":"system","method":"ExtrinsicSuccess","data":[{"weight":{"refTime":"255,250,000","proofSize":"0"},"class":"Mandatory","paysFee":"Yes"}]}]}}},"16979317":{"convictionVoting":{"vote":{"index":0,"signer":"J9ABr4JCLTVbFrZASCxVz5Sspi6LMdYwVNZWinpyidn13xE","args":["114","{\"standard\":{\"vote\":\"0x00\",\"balance\":5000000000000}}"],"events":[{"section":"system","method":"ExtrinsicSuccess","data":[{"weight":{"refTime":"255,250,000","proofSize":"0"},"class":"Mandatory","paysFee":"Yes"}]}]}}},"16979507":{"convictionVoting":{"vote":{"index":0,"signer":"G4UB5DJvfycaDNaUad21LQqjJVzBoTki1gf7PbKtMUowDwv","args":["116","{\"standard\":{\"vote\":\"0x00\",\"balance\":1200000000000}}"],"events":[{"section":"system","method":"ExtrinsicSuccess","data":[{"weight":{"refTime":"255,250,000","proofSize":"0"},"class":"Mandatory","paysFee":"Yes"}]}]}}},"16979513":{"convictionVoting":{"vote":{"index":0,"signer":"G4UB5DJvfycaDNaUad21LQqjJVzBoTki1gf7PbKtMUowDwv","args":["117","{\"standard\":{\"vote\":\"0x00\",\"balance\":1200000000000}}"],"events":[{"section":"system","method":"ExtrinsicSuccess","data":[{"weight":{"refTime":"255,250,000","proofSize":"0"},"class":"Mandatory","paysFee":"Yes"}]}]}}},"16979519":{"convictionVoting":{"vote":{"index":0,"signer":"G4UB5DJvfycaDNaUad21LQqjJVzBoTki1gf7PbKtMUowDwv","args":["118","{\"standard\":{\"vote\":\"0x80\",\"balance\":1200000000000}}"],"events":[{"section":"system","method":"ExtrinsicSuccess","data":[{"weight":{"refTime":"255,250,000","proofSize":"0"},"class":"Mandatory","paysFee":"Yes"}]}]}}},"16979527":{"convictionVoting":{"vote":{"index":0,"signer":"G4UB5DJvfycaDNaUad21LQqjJVzBoTki1gf7PbKtMUowDwv","args":["119","{\"standard\":{\"vote\":\"0x80\",\"balance\":1200000000000}}"],"events":[{"section":"system","method":"ExtrinsicSuccess","data":[{"weight":{"refTime":"255,250,000","proofSize":"0"},"class":"Mandatory","paysFee":"Yes"}]}]}}},"16979537":{"convictionVoting":{"vote":{"index":0,"signer":"G4UB5DJvfycaDNaUad21LQqjJVzBoTki1gf7PbKtMUowDwv","args":["120","{\"standard\":{\"vote\":\"0x00\",\"balance\":1200000000000}}"],"events":[{"section":"system","method":"ExtrinsicSuccess","data":[{"weight":{"refTime":"255,250,000","proofSize":"0"},"class":"Mandatory","paysFee":"Yes"}]}]}}},"16979542":{"convictionVoting":{"vote":{"index":0,"signer":"G4UB5DJvfycaDNaUad21LQqjJVzBoTki1gf7PbKtMUowDwv","args":["119","{\"standard\":{\"vote\":\"0x00\",\"balance\":1200000000000}}"],"events":[{"section":"system","method":"ExtrinsicSuccess","data":[{"weight":{"refTime":"255,250,000","proofSize":"0"},"class":"Mandatory","paysFee":"Yes"}]}]}}},"16979551":{"convictionVoting":{"vote":{"index":0,"signer":"G4UB5DJvfycaDNaUad21LQqjJVzBoTki1gf7PbKtMUowDwv","args":["121","{\"standard\":{\"vote\":\"0x00\",\"balance\":1200000000000}}"],"events":[{"section":"system","method":"ExtrinsicSuccess","data":[{"weight":{"refTime":"255,250,000","proofSize":"0"},"class":"Mandatory","paysFee":"Yes"}]}]}}},"16979555":{"convictionVoting":{"vote":{"index":0,"signer":"G4UB5DJvfycaDNaUad21LQqjJVzBoTki1gf7PbKtMUowDwv","args":["122","{\"standard\":{\"vote\":\"0x80\",\"balance\":1200000000000}}"],"events":[{"section":"system","method":"ExtrinsicSuccess","data":[{"weight":{"refTime":"255,250,000","proofSize":"0"},"class":"Mandatory","paysFee":"Yes"}]}]}}},"16979808":{"convictionVoting":{"vote":{"index":0,"signer":"GbmW3q2Hv5UaiRreQuBtevXb8DHdvsRFkBGXe2Xz1Y9FM8a","args":["122","{\"standard\":{\"vote\":\"0x81\",\"balance\":53000000000000}}"],"events":[{"section":"system","method":"ExtrinsicSuccess","data":[{"weight":{"refTime":"255,250,000","proofSize":"0"},"class":"Mandatory","paysFee":"Yes"}]}]}}},"16980319":{"convictionVoting":{"vote":{"index":0,"signer":"CzB1XBwkko3Az7DNZDPigZ1bjzLxELAGnLBnFGRdQ4PXTqZ","args":["114","{\"standard\":{\"vote\":\"0x81\",\"balance\":50000000000000}}"],"events":[{"section":"system","method":"ExtrinsicSuccess","data":[{"weight":{"refTime":"255,250,000","proofSize":"0"},"class":"Mandatory","paysFee":"Yes"}]}]}}},"16980326":{"convictionVoting":{"vote":{"index":0,"signer":"CzB1XBwkko3Az7DNZDPigZ1bjzLxELAGnLBnFGRdQ4PXTqZ","args":["117","{\"standard\":{\"vote\":\"0x01\",\"balance\":50000000000000}}"],"events":[{"section":"system","method":"ExtrinsicSuccess","data":[{"weight":{"refTime":"255,250,000","proofSize":"0"},"class":"Mandatory","paysFee":"Yes"}]}]}}},"16980330":{"convictionVoting":{"vote":{"index":0,"signer":"CzB1XBwkko3Az7DNZDPigZ1bjzLxELAGnLBnFGRdQ4PXTqZ","args":["118","{\"standard\":{\"vote\":\"0x81\",\"balance\":50000000000000}}"],"events":[{"section":"system","method":"ExtrinsicSuccess","data":[{"weight":{"refTime":"255,250,000","proofSize":"0"},"class":"Mandatory","paysFee":"Yes"}]}]}}},"16980336":{"convictionVoting":{"vote":{"index":0,"signer":"CzB1XBwkko3Az7DNZDPigZ1bjzLxELAGnLBnFGRdQ4PXTqZ","args":["109","{\"standard\":{\"vote\":\"0x83\",\"balance\":50000000000000}}"],"events":[{"section":"system","method":"ExtrinsicSuccess","data":[{"weight":{"refTime":"255,250,000","proofSize":"0"},"class":"Mandatory","paysFee":"Yes"}]}]}}},"16980340":{"convictionVoting":{"vote":{"index":0,"signer":"CzB1XBwkko3Az7DNZDPigZ1bjzLxELAGnLBnFGRdQ4PXTqZ","args":["111","{\"standard\":{\"vote\":\"0x83\",\"balance\":50000000000000}}"],"events":[{"section":"system","method":"ExtrinsicSuccess","data":[{"weight":{"refTime":"255,250,000","proofSize":"0"},"class":"Mandatory","paysFee":"Yes"}]}]}}},"16980352":{"convictionVoting":{"vote":{"index":0,"signer":"Hgjqt5NUcKzNckgz23xfaJL89onmvmTrywZ6xH5FhY7LfKG","args":["122","{\"standard\":{\"vote\":\"0x81\",\"balance\":57000000000000}}"],"events":[{"section":"system","method":"ExtrinsicSuccess","data":[{"weight":{"refTime":"255,250,000","proofSize":"0"},"class":"Mandatory","paysFee":"Yes"}]}]}}},"16981625":{"convictionVoting":{"vote":{"index":0,"signer":"HkRdC1w5XDvQQadAS2nL58mPRBCLyUCZAAiaV7DUWJgj7P8","args":["122","{\"standard\":{\"vote\":\"0x85\",\"balance\":75000000000000}}"],"events":[{"section":"system","method":"ExtrinsicSuccess","data":[{"weight":{"refTime":"255,250,000","proofSize":"0"},"class":"Mandatory","paysFee":"Yes"}]}]}}},"16981803":{"convictionVoting":{"vote":{"index":0,"signer":"DDhVgn62SE2riWjS6U4AaYtfLNKuFxqTU32EnqAtAuxqM58","args":["122","{\"standard\":{\"vote\":\"0x81\",\"balance\":82000000000000}}"],"events":[{"section":"system","method":"ExtrinsicSuccess","data":[{"weight":{"refTime":"255,250,000","proofSize":"0"},"class":"Mandatory","paysFee":"Yes"}]}]}}},"16981825":{"convictionVoting":{"vote":{"index":0,"signer":"D3bV95NADtJa8H2xTuq9raaXbniwZWM7b5rqHx4rHffL3o8","args":["118","{\"standard\":{\"vote\":\"0x81\",\"balance\":10537023945930}}"],"events":[{"section":"system","method":"ExtrinsicSuccess","data":[{"weight":{"refTime":"255,250,000","proofSize":"0"},"class":"Mandatory","paysFee":"Yes"}]}]}}},"16981827":{"convictionVoting":{"vote":{"index":0,"signer":"D3bV95NADtJa8H2xTuq9raaXbniwZWM7b5rqHx4rHffL3o8","args":["109","{\"standard\":{\"vote\":\"0x81\",\"balance\":10537023945930}}"],"events":[{"section":"system","method":"ExtrinsicSuccess","data":[{"weight":{"refTime":"255,250,000","proofSize":"0"},"class":"Mandatory","paysFee":"Yes"}]}]}}},"16982291":{"convictionVoting":{"vote":{"index":0,"signer":"F7wsyovZnzJD5ZGdCRrUrf3GuyjeLuMuaxWU2cpFSXYVz9p","args":["122","{\"standard\":{\"vote\":\"0x81\",\"balance\":1400000000000}}"],"events":[{"section":"system","method":"ExtrinsicSuccess","data":[{"weight":{"refTime":"255,250,000","proofSize":"0"},"class":"Mandatory","paysFee":"Yes"}]}]}}},"16982512":{"convictionVoting":{"vote":{"index":0,"signer":"DYEcn7dPMULzdrz5rTdhTToK7AKAvrSsmfqSPQd4q2JMn9f","args":["119","{\"standard\":{\"vote\":\"0x81\",\"balance\":1000000000000}}"],"events":[{"section":"system","method":"ExtrinsicSuccess","data":[{"weight":{"refTime":"255,250,000","proofSize":"0"},"class":"Mandatory","paysFee":"Yes"}]}]}}},"16982524":{"convictionVoting":{"vote":{"index":0,"signer":"DYEcn7dPMULzdrz5rTdhTToK7AKAvrSsmfqSPQd4q2JMn9f","args":["120","{\"standard\":{\"vote\":\"0x01\",\"balance\":1000000000000}}"],"events":[{"section":"system","method":"ExtrinsicSuccess","data":[{"weight":{"refTime":"255,250,000","proofSize":"0"},"class":"Mandatory","paysFee":"Yes"}]}]}}},"16982537":{"convictionVoting":{"vote":{"index":0,"signer":"DYEcn7dPMULzdrz5rTdhTToK7AKAvrSsmfqSPQd4q2JMn9f","args":["121","{\"standard\":{\"vote\":\"0x01\",\"balance\":1000000000000}}"],"events":[{"section":"system","method":"ExtrinsicSuccess","data":[{"weight":{"refTime":"255,250,000","proofSize":"0"},"class":"Mandatory","paysFee":"Yes"}]}]}}},"16982547":{"convictionVoting":{"vote":{"index":0,"signer":"DYEcn7dPMULzdrz5rTdhTToK7AKAvrSsmfqSPQd4q2JMn9f","args":["122","{\"standard\":{\"vote\":\"0x81\",\"balance\":1000000000000}}"],"events":[{"section":"system","method":"ExtrinsicSuccess","data":[{"weight":{"refTime":"255,250,000","proofSize":"0"},"class":"Mandatory","paysFee":"Yes"}]}]}}},"16982597":{"convictionVoting":{"vote":{"index":0,"signer":"HnEhWv595YMcYPFrTZAQBC4Q8wnoj3nLAfTHpbk6nbBurFY","args":["122","{\"standard\":{\"vote\":\"0x81\",\"balance\":10000000000000}}"],"events":[{"section":"system","method":"ExtrinsicSuccess","data":[{"weight":{"refTime":"255,250,000","proofSize":"0"},"class":"Mandatory","paysFee":"Yes"}]}]}}},"16982598":{"convictionVoting":{"vote":{"index":0,"signer":"EfkeewT5dhAtX7guAuiQ3zHcMAAZm2NvG5iqEdApyCd4Xpm","args":["122","{\"standard\":{\"vote\":\"0x81\",\"balance\":10210200000000}}"],"events":[{"section":"system","method":"ExtrinsicSuccess","data":[{"weight":{"refTime":"255,250,000","proofSize":"0"},"class":"Mandatory","paysFee":"Yes"}]}]}}}}}